runzero/__init__.py
runzero/api/__init__.py
runzero/api/admin/__init__.py
runzero/api/admin/_sdk_source_icon.py
runzero/api/admin/custom_integrations.py
runzero/api/admin/orgs.py
runzero/api/admin/tasks.py
runzero/api/custom_integrations.py
runzero/api/explorers.py
runzero/api/hosted_zones.py
runzero/api/imports/__init__.py
runzero/api/imports/assets.py
runzero/api/scans.py
runzero/api/sites.py
runzero/api/tasks.py
runzero/client/__init__.py
runzero/client/_http/__init__.py
runzero/client/_http/auth.py
runzero/client/_http/io.py
runzero/client/client.py
runzero/client/errors.py
runzero/errors.py
runzero/py.typed
runzero/types/__init__.py
runzero/types/_data_models_gen.py
runzero/types/_rate_limit_information.py
runzero/types/_wrapped.py
runzero/types/errors.py
runzero/version.py
runzero_sdk-0.8.7.dist-info/METADATA
runzero_sdk-0.8.7.dist-info/WHEEL
runzero_sdk-0.8.7.dist-info/licenses/LICENSE
runzero_sdk-0.8.7.dist-info/RECORD
