Metadata-Version: 2.4
Name: runzero-sdk
Version: 0.8.7
Summary: The runZero platform sdk
License: BSD-2-Clause
License-File: LICENSE
Keywords: runzero,api,sdk
Author: runZero
Author-email: support@runzero.com
Requires-Python: >=3.8,<4.0
Classifier: Development Status :: 4 - Beta
Classifier: Framework :: Pydantic
Classifier: Intended Audience :: Developers
Classifier: Intended Audience :: System Administrators
Classifier: License :: OSI Approved :: BSD License
Classifier: Programming Language :: Python :: 3
Classifier: Programming Language :: Python :: 3.8
Classifier: Programming Language :: Python :: 3.9
Classifier: Programming Language :: Python :: 3.10
Classifier: Programming Language :: Python :: 3.11
Classifier: Programming Language :: Python :: 3.12
Classifier: Programming Language :: Python :: 3.13
Classifier: Programming Language :: Python :: 3.14
Classifier: Topic :: Security
Classifier: Topic :: Software Development :: Libraries :: Python Modules
Classifier: Topic :: System :: Systems Administration
Classifier: Typing :: Typed
Requires-Dist: certifi (>=2024.2.2)
Requires-Dist: pydantic (>=1.10.5,<2.0.0)
Requires-Dist: requests (>=2.32.3,<3.0.0)
Project-URL: Documentation, https://runzeroinc.github.io/runzero-sdk-py
Project-URL: Homepage, https://runzero.com/
Project-URL: Repository, https://github.com/runZeroInc/runzero-sdk-py
